pyreportgen/__init__.py
pyreportgen/base.py
pyreportgen/gis.py
pyreportgen/helpers.py
pyreportgen/layout.py
pyreportgen/statistic.py
pyreportgen/style.py
pyreportgen-0.1.17.dist-info/METADATA
pyreportgen-0.1.17.dist-info/WHEEL
pyreportgen-0.1.17.dist-info/top_level.txt
pyreportgen-0.1.17.dist-info/RECORD
