Metadata-Version: 2.1
Name: pyreportgen
Version: 0.1.17
Summary: A package for creating reports and other pdf documents.
Classifier: Programming Language :: Python :: 3
Classifier: License :: OSI Approved :: MIT License
Classifier: Operating System :: OS Independent
Requires-Python: >=3.6
